MANIFEST.in
README.rst
gpl-3.0.txt
setup.py
doc/COPYING
doc/Makefile
doc/attributes.rst
doc/classes.rst
doc/conf.py
doc/construction.rst
doc/delegation.rst
doc/index.rst
doc/modifiers.rst
doc/roles.rst
elk/__init__.py
elk/attribute.py
elk/elk.py
elk/meta.py
elk/modifier.py
elk/test_attr.py
elk/test_attribute_builder.py
elk/test_attribute_construction.py
elk/test_attribute_default.py
elk/test_attribute_delegation.py
elk/test_attribute_init_arg.py
elk/test_attribute_initialisation.py
elk/test_attribute_lazy.py
elk/test_attribute_mode.py
elk/test_attribute_required.py
elk/test_attribute_type.py
elk/test_build.py
elk/test_buildargs.py
elk/test_meta.py
elk/test_modifier.py
elk/test_roles.py
elk.egg-info/PKG-INFO
elk.egg-info/SOURCES.txt
elk.egg-info/dependency_links.txt
elk.egg-info/top_level.txt