Metadata-Version: 1.1
Name: elk
Version: 0.3
Summary: Moose-like object system for Python
Home-page: https://frasertweedale.github.io/elk
Author: Fraser Tweedale
Author-email: frase@frase.id.au
License: UNKNOWN
Platform: UNKNOWN
Classifier: Development Status :: 3 - Alpha
Classifier: Intended Audience :: Developers
Classifier: Intended Audience :: Information Technology
Classifier: License :: OSI Approved :: GNU General Public License v3 or later (GPLv3+)
Classifier: Topic :: Software Development
Classifier: Topic :: Software Development :: Libraries
